aiolog/__init__.py
aiolog/base.py
aiolog/smtp.py
aiolog/telegram.py
aiolog-0.1.1.dist-info/LICENSE
aiolog-0.1.1.dist-info/METADATA
aiolog-0.1.1.dist-info/WHEEL
aiolog-0.1.1.dist-info/top_level.txt
aiolog-0.1.1.dist-info/RECORD
