Metadata-Version: 2.1
Name: aiolog
Version: 0.1.1
Summary: Asynchronous handlers for standard python logging library
Home-page: https://github.com/imbolc/aiolog
Author: Imbolc
Author-email: imbolc@imbolc.name
License: ISC
Keywords: logging,asyncio
Platform: UNKNOWN
Classifier: License :: OSI Approved :: ISC License (ISCL)
Classifier: Intended Audience :: Developers
Classifier: Programming Language :: Python :: 3
Classifier: Programming Language :: Python :: 3.5
Classifier: Programming Language :: Python :: 3 :: Only
Requires-Dist: async-timeout (>=1.1.0)
